{
    "server_port": 3000,
    "maxSocketListeners": 20,
    "secure": true,
    "secureconfig": {
        "key": "src/assets/key.pem",
        "cert": "src/assets/cert.pem",
        "passphrase": "localhost"
    },
    "mysql": {
        "connectionLimit" : 10,
        "host"            : "...",
        "user"            : "...",
        "password"        : "...",
        "database"        : "friends"
    },
    "firebaseAuth": {
        "forceAuth"         : true,
        "emailVerification" : false,
        "firebase": {
            "apiKey"            : "...",
            "authDomain"        : "...",
            "databaseURL"       : "...",
            "projectId"         : "...",
            "storageBucket"     : "",
            "messagingSenderId" : "...",
            "appId":            "..."
        }
    }
}